README.md
setup.cfg
setup.py
distributions_test_example/Binomialdistribution.py
distributions_test_example/Gaussiandistribution.py
distributions_test_example/Generaldistribution.py
distributions_test_example/__init__.py
distributions_test_example.egg-info/PKG-INFO
distributions_test_example.egg-info/SOURCES.txt
distributions_test_example.egg-info/dependency_links.txt
distributions_test_example.egg-info/not-zip-safe
distributions_test_example.egg-info/top_level.txt