Metadata-Version: 1.1
Name: distributions-test-example
Version: 0.1
Summary: Gaussian distributions
Home-page: UNKNOWN
Author: Xu Jiang
Author-email: x.jiang@strath.com
License: UNKNOWN
Platform: UNKNOWN
Classifier: Programming Language :: Python :: 3
Classifier: License :: OSI Approved :: MIT License
Classifier: Operating System :: OS Independent
